motleycache/__init__.py
motleycache/caching.py
motleycache/http_cache.py
motleycache/utils.py
motleycache-0.0.4.dist-info/LICENSE
motleycache-0.0.4.dist-info/METADATA
motleycache-0.0.4.dist-info/WHEEL
motleycache-0.0.4.dist-info/RECORD
