Metadata-Version: 2.1
Name: motleycache
Version: 0.0.4
Summary: Package for caching http requests
Author: MotleyCrew
Author-email: github@motleycrew.ai
Requires-Python: >=3.10,<4.0
Classifier: Programming Language :: Python :: 3
Classifier: Programming Language :: Python :: 3.10
Classifier: Programming Language :: Python :: 3.11
Classifier: Programming Language :: Python :: 3.12
Provides-Extra: lunary
Requires-Dist: cloudpickle (>=3.0.0,<4.0.0)
Requires-Dist: curl-cffi (>=0.6.4,<0.7.0)
Requires-Dist: httpx (>=0.27.0,<0.28.0)
Requires-Dist: lunary (>=1.0.21,<2.0.0) ; extra == "lunary"
Requires-Dist: platformdirs (>=4.2.1,<5.0.0)
Requires-Dist: pytest (>=8.0.2,<9.0.0)
Requires-Dist: pytest-cov (>=4.1.0,<5.0.0)
Requires-Dist: requests (>=2.31.0,<3.0.0)
